agentflow/__init__.py
agentflow/agentflow.py
agentflow-0.0.2.dist-info/LICENSE
agentflow-0.0.2.dist-info/METADATA
agentflow-0.0.2.dist-info/WHEEL
agentflow-0.0.2.dist-info/top_level.txt
agentflow-0.0.2.dist-info/RECORD
