Metadata-Version: 2.1
Name: agentflow
Version: 0.0.2
Summary: A library for creating agents.
Author: Stoyan Stoyanov
Project-URL: Homepage, https://github.com/stoyan-stoyanov/llmflow
Project-URL: github, https://github.com/stoyan-stoyanov/llmflow
Classifier: Programming Language :: Python :: 3
Classifier: License :: OSI Approved :: MIT License
Classifier: Operating System :: OS Independent
Requires-Python: >=3.9
License-File: LICENSE
Requires-Dist: urllib3 (==1.26.15)
